pygments_djc/__init__.py
pygments_djc/lexers.py
pygments_djc/py.typed
pygments_djc-1.0.1.dist-info/LICENSE
pygments_djc-1.0.1.dist-info/METADATA
pygments_djc-1.0.1.dist-info/WHEEL
pygments_djc-1.0.1.dist-info/top_level.txt
pygments_djc-1.0.1.dist-info/RECORD
