Metadata-Version: 2.2
Name: pygments_djc
Version: 1.0.1
Summary: Pygments Lexers for django-components
Author-email: Juro Oravec <juraj.oravec.josefson@gmail.com>
License: MIT
Project-URL: Homepage, https://github.com/django-components/pygments-djc/
Keywords: django,components,pygments,lexer,html,js,css
Classifier: Framework :: Django
Classifier: Operating System :: OS Independent
Classifier: Programming Language :: Python
Classifier: Programming Language :: Python :: 3
Classifier: Programming Language :: Python :: 3.8
Classifier: Programming Language :: Python :: 3.9
Classifier: Programming Language :: Python :: 3.10
Classifier: Programming Language :: Python :: 3.11
Classifier: Programming Language :: Python :: 3.12
Classifier: Programming Language :: Python :: 3.13
Requires-Python: <4.0,>=3.8
License-File: LICENSE
Requires-Dist: pygments>=2.15
